LICENSE.txt
MANIFEST.in
README.md
setup.cfg
setup.py
django_cache_decorator/__init__.py
django_cache_decorator/utils.py
django_cache_decorator.egg-info/PKG-INFO
django_cache_decorator.egg-info/SOURCES.txt
django_cache_decorator.egg-info/dependency_links.txt
django_cache_decorator.egg-info/top_level.txt