Metadata-Version: 1.1
Name: django-cache-decorator
Version: 0.4.1
Summary: Easily add caching to functions within a django project.
Home-page: https://github.com/rchrd2/django-cache-decorator/
Author: Richard Caceres
Author-email: me@rchrd.net
License: MIT
Download-URL: https://github.com/rchrd2/django-cache-decorator/tarball/0.4.1
Keywords: django,caching,decorator
Platform: UNKNOWN
